{
  "doctype": "DocType",
  "name": "LMS Group Member",
  "module": "Lms Saas",
  "custom": 0,
  "istable": 1,
  "fields": [
    {"fieldname": "customer", "fieldtype": "Link", "label": "Customer", "options": "Customer", "reqd": 1, "in_list_view": 1},
    {"fieldname": "member_role", "fieldtype": "Select", "label": "Role", "options": "Leader\nMember", "default": "Member", "in_list_view": 1},
    {"fieldname": "joined_on", "fieldtype": "Date", "label": "Joined On", "default": "Today"}
  ],
  "permissions": []
}
